lmfast/__init__.py
lmfast/alignment.py
lmfast/function_calling.py
lmfast/pretraining.py
lmfast/reasoning.py
lmfast/agents/core.py
lmfast/agents/specialized.py
lmfast/cli/__init__.py
lmfast/cli/main.py
lmfast/core/__init__.py
lmfast/core/config.py
lmfast/core/models.py
lmfast/deployment/__init__.py
lmfast/deployment/browser.py
lmfast/distillation/__init__.py
lmfast/distillation/advanced.py
lmfast/distillation/self_distillation.py
lmfast/distillation/teacher_student.py
lmfast/guardrails/__init__.py
lmfast/guardrails/config.py
lmfast/guardrails/input_validator.py
lmfast/guardrails/output_filter.py
lmfast/inference/__init__.py
lmfast/inference/quantization.py
lmfast/inference/server.py
lmfast/inference/speculative.py
lmfast/mcp/server.py
lmfast/observability/__init__.py
lmfast/observability/explainability.py
lmfast/observability/metrics.py
lmfast/observability/tracing.py
lmfast/rag/__init__.py
lmfast/rag/lightweight.py
lmfast/training/__init__.py
lmfast/training/data.py
lmfast/training/optimizations.py
lmfast/training/trainer.py
lmfast/utils/colab.py
lmfast/utils/structured.py
lmfast-0.3.5.dist-info/METADATA
lmfast-0.3.5.dist-info/WHEEL
lmfast-0.3.5.dist-info/entry_points.txt
lmfast-0.3.5.dist-info/licenses/LICENSE
lmfast-0.3.5.dist-info/RECORD
