Metadata-Version: 2.4
Name: lmfast
Version: 0.3.5
Summary: Democratized Small Language Model Training - Train, fine-tune, distill, and deploy sub-500M parameter models on Colab T4 in 30-40 minutes
Project-URL: Homepage, https://github.com/2796gaurav/LMFast
Project-URL: Documentation, https://lmfast.readthedocs.io
Project-URL: Repository, https://github.com/2796gaurav/LMFast
Project-URL: Issues, https://github.com/2796gaurav/LMFast/issues
Author-email: Gaurav Chauhan <2796gaurav@gmail.com>
License: Apache-2.0
License-File: LICENSE
Keywords: deep-learning,distillation,fine-tuning,huggingface,llm,machine-learning,pytorch,slm,small-language-models,transformers
Classifier: Development Status :: 4 - Beta
Classifier: Intended Audience :: Developers
Classifier: Intended Audience :: Science/Research
Classifier: License :: OSI Approved :: Apache Software License
Classifier: Programming Language :: Python :: 3
Classifier: Programming Language :: Python :: 3.10
Classifier: Programming Language :: Python :: 3.11
Classifier: Programming Language :: Python :: 3.12
Classifier: Topic :: Scientific/Engineering :: Artificial Intelligence
Requires-Python: >=3.10
Requires-Dist: accelerate>=0.28.0
Requires-Dist: bitsandbytes>=0.43.0
Requires-Dist: datasets>=2.18.0
Requires-Dist: mcp>=0.1.0
Requires-Dist: numpy>=1.24.0
Requires-Dist: peft>=0.10.0
Requires-Dist: pydantic-settings>=2.0.0
Requires-Dist: pydantic>=2.0.0
Requires-Dist: pyyaml>=6.0
Requires-Dist: rich>=13.0.0
Requires-Dist: torch>=2.1.0
Requires-Dist: tqdm>=4.65.0
Requires-Dist: transformers>=4.40.0
Requires-Dist: trl>=0.8.0
Requires-Dist: typer>=0.9.0
Provides-Extra: all
Requires-Dist: black>=24.0.0; extra == 'all'
Requires-Dist: detoxify>=0.5.0; extra == 'all'
Requires-Dist: fastapi>=0.109.0; extra == 'all'
Requires-Dist: jedi>=0.16; extra == 'all'
Requires-Dist: langfuse>=2.0.0; extra == 'all'
Requires-Dist: matplotlib>=3.7.0; extra == 'all'
Requires-Dist: mypy>=1.8.0; extra == 'all'
Requires-Dist: opentelemetry-api>=1.20.0; extra == 'all'
Requires-Dist: opentelemetry-sdk>=1.20.0; extra == 'all'
Requires-Dist: pre-commit>=3.6.0; extra == 'all'
Requires-Dist: presidio-analyzer>=2.2.0; extra == 'all'
Requires-Dist: presidio-anonymizer>=2.2.0; extra == 'all'
Requires-Dist: pytest-asyncio>=0.23.0; extra == 'all'
Requires-Dist: pytest-cov>=4.1.0; extra == 'all'
Requires-Dist: pytest>=8.0.0; extra == 'all'
Requires-Dist: ruff>=0.2.0; extra == 'all'
Requires-Dist: seaborn>=0.12.0; extra == 'all'
Requires-Dist: unsloth[colab-new]>=2024.1; extra == 'all'
Requires-Dist: uvicorn>=0.27.0; extra == 'all'
Requires-Dist: vllm>=0.4.0; extra == 'all'
Provides-Extra: dev
Requires-Dist: black>=24.0.0; extra == 'dev'
Requires-Dist: jedi>=0.16; extra == 'dev'
Requires-Dist: mypy>=1.8.0; extra == 'dev'
Requires-Dist: pre-commit>=3.6.0; extra == 'dev'
Requires-Dist: pytest-asyncio>=0.23.0; extra == 'dev'
Requires-Dist: pytest-cov>=4.1.0; extra == 'dev'
Requires-Dist: pytest>=8.0.0; extra == 'dev'
Requires-Dist: ruff>=0.2.0; extra == 'dev'
Provides-Extra: fast
Requires-Dist: unsloth[colab-new]>=2024.1; extra == 'fast'
Provides-Extra: guardrails
Requires-Dist: detoxify>=0.5.0; extra == 'guardrails'
Requires-Dist: presidio-analyzer>=2.2.0; extra == 'guardrails'
Requires-Dist: presidio-anonymizer>=2.2.0; extra == 'guardrails'
Provides-Extra: inference
Requires-Dist: fastapi>=0.109.0; extra == 'inference'
Requires-Dist: uvicorn>=0.27.0; extra == 'inference'
Requires-Dist: vllm>=0.4.0; extra == 'inference'
Provides-Extra: observability
Requires-Dist: langfuse>=2.0.0; extra == 'observability'
Requires-Dist: matplotlib>=3.7.0; extra == 'observability'
Requires-Dist: opentelemetry-api>=1.20.0; extra == 'observability'
Requires-Dist: opentelemetry-sdk>=1.20.0; extra == 'observability'
Requires-Dist: seaborn>=0.12.0; extra == 'observability'
